{"histograms":{"stats":[{"mean":23.0296,"max":44,"basesPerBin":"20"},{"max":50,"basesPerBin":"40","mean":26.9384},{"basesPerBin":"100","max":70,"mean":38.384},{"mean":57.772,"max":88,"basesPerBin":"200"},{"basesPerBin":"400","max":130,"mean":96.064},{"basesPerBin":"1000","max":244,"mean":211.26}],"meta":[{"basesPerBin":"20","arrayParams":{"urlTemplate":"hist-20-{Chunk}.json","length":2500,"chunkSize":10000}},{"arrayParams":{"length":1250,"urlTemplate":"hist-40-{Chunk}.json","chunkSize":10000},"basesPerBin":"40"},{"arrayParams":{"chunkSize":10000,"urlTemplate":"hist-100-{Chunk}.json","length":500},"basesPerBin":"100"},{"basesPerBin":"200","arrayParams":{"urlTemplate":"hist-200-{Chunk}.json","length":250,"chunkSize":10000}},{"arrayParams":{"urlTemplate":"hist-400-{Chunk}.json","length":125,"chunkSize":10000},"basesPerBin":"400"},{"arrayParams":{"chunkSize":10000,"urlTemplate":"hist-1000-{Chunk}.json","length":50},"basesPerBin":"1000"}]},"featureCount":9596,"intervals":{"nclist":[[1,2,15272,1],[1,15173,29227,2],[1,29127,43440,3],[1,43341,49986,4]],"lazyClass":1,"classes":[{"attributes":["Start","End","Strand"],"isArrayAttr":{}},{"isArrayAttr":{"Sublist":1},"attributes":["Start","End","Chunk"]}],"count":9596,"urlTemplate":"lf-{Chunk}.json","maxEnd":49986,"minStart":2},"formatVersion":1}